h2o/h2o.c
h2o/ch2o.pxd
h2o/__init__.py
h2o/h2o.so
h2o/h2o.pyx
pyh2o-0.0.6.dist-info/top_level.txt
pyh2o-0.0.6.dist-info/METADATA
pyh2o-0.0.6.dist-info/metadata.json
pyh2o-0.0.6.dist-info/DESCRIPTION.rst
pyh2o-0.0.6.dist-info/RECORD
pyh2o-0.0.6.dist-info/WHEEL
